ising_toolkit/__init__.py
ising_toolkit/api.py
ising_toolkit/client.py
ising_toolkit/request/GeneralTaskCreateRequest.py
ising_toolkit/request/TemplateTaskCreateRequest.py
ising_toolkit/request/__init__.py
ising_toolkit-1.0.3.dist-info/METADATA
ising_toolkit-1.0.3.dist-info/WHEEL
ising_toolkit-1.0.3.dist-info/top_level.txt
ising_toolkit-1.0.3.dist-info/RECORD
