Metadata-Version: 2.4
Name: ising_toolkit
Version: 1.0.3
Summary: Python SDK for Ising Cloud Service
Home-page: https://github.com/isingcloud/ising-cloud-sdk
Author: IsingTech
Author-email: haojunjie@isingtech.com
Classifier: Programming Language :: Python :: 3
Classifier: License :: OSI Approved :: MIT License
Classifier: Operating System :: OS Independent
Requires-Python: >=3.8
Requires-Dist: requests>=2.22.0
Dynamic: author
Dynamic: author-email
Dynamic: classifier
Dynamic: description
Dynamic: description-content-type
Dynamic: home-page
Dynamic: requires-dist
Dynamic: requires-python
Dynamic: summary
